interfacemaster/__init__.py
interfacemaster/__version__.py
interfacemaster/brute_force.py
interfacemaster/cellcalc.py
interfacemaster/hetero_searching.py
interfacemaster/interface_generator.py
interfacemaster/run_brute_force_symmetric_tilt.py
interfacemaster/symmetric_tilt.py
interfacemaster/tool.py
interfacemaster-1.1.7.dist-info/LICENSE.md
interfacemaster-1.1.7.dist-info/METADATA
interfacemaster-1.1.7.dist-info/WHEEL
interfacemaster-1.1.7.dist-info/top_level.txt
interfacemaster-1.1.7.dist-info/RECORD
